libsfile/__init__.py
libsfile/analysis.py
libsfile/hashes.py
plugins/__init__.py
plugins/docx.py
plugins/exif.py
plugins/media.py
plugins/pdf.py
plugins/pe.py
plugins/xlsx.py
sfile/__init__.py
sfile/sfile.py
py_sfile-0.1.1.dist-info/LICENSE
py_sfile-0.1.1.dist-info/METADATA
py_sfile-0.1.1.dist-info/WHEEL
py_sfile-0.1.1.dist-info/entry_points.txt
py_sfile-0.1.1.dist-info/top_level.txt
py_sfile-0.1.1.dist-info/RECORD
