Metadata-Version: 2.1
Name: py-sfile
Version: 0.1.1
Summary: sfile, cross platform file metadata analyzer
Home-page: https://github.com/gcarmix/sfile
Download-URL: https://github.com/gcarmix/sfile/archive/master.zip
Author: gcarmix
Author-email: carmixdev@gmail.com
Maintainer: gcarmix
Maintainer-email: carmixdev@gmail.com
License: MIT
Project-URL: Bug Tracker, https://github.com/gcarmix/sfile/issues
Project-URL: Documentation, https://github.com/gcarmix/sfile/blob/master/README.md
Project-URL: Source Code, https://github.com/gcarmix/sfile.git
Platform: LINUX
Platform: MAC
Platform: WINDOWS
License-File: LICENSE
Requires-Dist: importlib-resources
Requires-Dist: python-docx
Requires-Dist: Pillow
Requires-Dist: python-ffmpeg
Requires-Dist: pikepdf
Requires-Dist: openpyxl
Requires-Dist: pefile
